{
    "Ar36": {
        "error": 0.00039250131064065314, 
        "filter_outliers_dict": {
            "filter_outliers": true, 
            "iterations": 1, 
            "std_devs": 2
        }, 
        "fit": "Linear", 
        "value": 0.02206195054414056
    }, 
    "Ar37": {
        "error": 0.009795418696896334, 
        "filter_outliers_dict": {
            "filter_outliers": true, 
            "iterations": 1, 
            "std_devs": 2
        }, 
        "fit": "linear", 
        "value": 0.5436923584184552
    }, 
    "Ar38": {
        "error": 0.004310958585019455, 
        "filter_outliers_dict": {
            "filter_outliers": true, 
            "iterations": 1, 
            "std_devs": 2
        }, 
        "fit": "linear", 
        "value": 0.4668090392740474
    }, 
    "Ar39": {
        "error": 0.014924435255500908, 
        "filter_outliers_dict": {
            "filter_outliers": true, 
            "iterations": 1, 
            "std_devs": 2
        }, 
        "fit": "Linear", 
        "value": 35.09455811404199
    }, 
    "Ar40": {
        "error": 0.023221135845169508, 
        "filter_outliers_dict": {
            "filter_outliers": true, 
            "iterations": 1, 
            "std_devs": 2
        }, 
        "fit": "Linear", 
        "value": 151.68592237465734
    }, 
    "PM41": {
        "error": 0.07300130310430498, 
        "filter_outliers_dict": {
            "filter_outliers": false, 
            "iterations": 1, 
            "std_devs": 2
        }, 
        "fit": "linear", 
        "value": -0.14349879335931792
    }
}