{
    "AX": {
        "error": 0.00494944354078458, 
        "filter_outliers_dict": {
            "filter_outliers": true, 
            "iterations": 1, 
            "std_devs": 2
        }, 
        "fit": "average", 
        "value": -0.07893589888956508
    }, 
    "CDD": {
        "error": 4.380826213163435e-06, 
        "filter_outliers_dict": {
            "filter_outliers": true, 
            "iterations": 1, 
            "std_devs": 10
        }, 
        "fit": "average", 
        "value": 1.7367631306857652e-05
    }, 
    "H1": {
        "error": 0.00375170317980014, 
        "filter_outliers_dict": {
            "filter_outliers": true, 
            "iterations": 1, 
            "std_devs": 2
        }, 
        "fit": "average", 
        "value": -0.03395884506878905
    }, 
    "H2": {
        "error": 0.005130691318834158, 
        "filter_outliers_dict": {
            "filter_outliers": true, 
            "iterations": 1, 
            "std_devs": 2
        }, 
        "fit": "average", 
        "value": -0.19306238669430056
    }, 
    "L1": {
        "error": 0.001802224743819964, 
        "filter_outliers_dict": {
            "filter_outliers": true, 
            "iterations": 1, 
            "std_devs": 2
        }, 
        "fit": "average", 
        "value": -0.02539932442629453
    }, 
    "L2": {
        "error": 0.004452764116479534, 
        "filter_outliers_dict": {
            "filter_outliers": true, 
            "iterations": 1, 
            "std_devs": 2
        }, 
        "fit": "average", 
        "value": -0.007171609169899896
    }
}