{
    "Ar36": {
        "error": 0.00018493750931325065, 
        "fit": "previous", 
        "references": [
            {
                "exclude": false, 
                "record_id": "bu-FC-J-7795"
            }
        ], 
        "value": 0.0053485295594518315
    }, 
    "Ar37": {
        "error": 0.00473161420600496, 
        "fit": "previous", 
        "references": [
            {
                "exclude": false, 
                "record_id": "bu-FC-J-7795"
            }
        ], 
        "value": 0.05132851116969684
    }, 
    "Ar38": {
        "error": 0.002228568648995412, 
        "fit": "previous", 
        "references": [
            {
                "exclude": false, 
                "record_id": "bu-FC-J-7795"
            }
        ], 
        "value": 0.007201575515747228
    }, 
    "Ar39": {
        "error": 0.008693240569385065, 
        "fit": "previous", 
        "references": [
            {
                "exclude": false, 
                "record_id": "bu-FC-J-7795"
            }
        ], 
        "value": 0.0264951894735383
    }, 
    "Ar40": {
        "error": 0.006832779806276847, 
        "fit": "previous", 
        "references": [
            {
                "exclude": false, 
                "record_id": "bu-FC-J-7795"
            }
        ], 
        "value": 0.37057163213095895
    }, 
    "PM41": {
        "error": 0.06452388608138131, 
        "fit": "previous", 
        "references": [
            {
                "exclude": false, 
                "record_id": "bu-FC-J-7795"
            }
        ], 
        "value": 0.029979363362743983
    }
}